blockcg/__init__.py
blockcg/blockcg.py
blockcg/cg.py
blockcg/util.py
blockcg-0.0.1.dist-info/METADATA
blockcg-0.0.1.dist-info/WHEEL
blockcg-0.0.1.dist-info/licenses/LICENSE
blockcg-0.0.1.dist-info/RECORD
